main.py
agent/__init__.py
agent/graph.py
agent/llm.py
agent/prompts.py
agent/states.py
agent/tools.py
agent/ui.py
coder_buddy-0.1.3.dist-info/licenses/LICENSE
coder_buddy-0.1.3.dist-info/METADATA
coder_buddy-0.1.3.dist-info/WHEEL
coder_buddy-0.1.3.dist-info/entry_points.txt
coder_buddy-0.1.3.dist-info/top_level.txt
coder_buddy-0.1.3.dist-info/RECORD
