Metadata-Version: 2.4
Name: coder-buddy
Version: 0.1.3
Summary: A Claude Code-style AI coding assistant built with LangGraph and GPT-4o
Author-email: Saket Garodia <saketgarodia1@gmail.com>
Maintainer-email: Saket Garodia <saketgarodia1@gmail.com>
License-Expression: MIT
Project-URL: Homepage, https://github.com/garodisk/CodeBuddy
Project-URL: Repository, https://github.com/garodisk/CodeBuddy
Project-URL: Documentation, https://github.com/garodisk/CodeBuddy#readme
Project-URL: Bug Tracker, https://github.com/garodisk/CodeBuddy/issues
Keywords: ai,coding,assistant,langgraph,gpt-4o,cli,terminal
Classifier: Development Status :: 3 - Alpha
Classifier: Intended Audience :: Developers
Classifier: Programming Language :: Python :: 3.12
Classifier: Environment :: Console
Classifier: Topic :: Software Development :: Code Generators
Requires-Python: >=3.12
License-File: LICENSE
Requires-Dist: langchain>=0.3.27
Requires-Dist: langchain-core>=0.3.72
Requires-Dist: langchain-openai>=0.1.8
Requires-Dist: langgraph>=0.6.3
Requires-Dist: pydantic>=2.11.7
Requires-Dist: python-dotenv>=1.1.1
Requires-Dist: rich>=14.0.0
Requires-Dist: prompt-toolkit>=3.0.0
Provides-Extra: anthropic
Requires-Dist: langchain-anthropic>=0.1.0; extra == "anthropic"
Provides-Extra: gemini
Requires-Dist: langchain-google-genai>=1.0.0; extra == "gemini"
Provides-Extra: groq
Requires-Dist: langchain-groq>=0.3.7; extra == "groq"
Requires-Dist: groq>=0.31.0; extra == "groq"
Provides-Extra: all
Requires-Dist: langchain-anthropic>=0.1.0; extra == "all"
Requires-Dist: langchain-google-genai>=1.0.0; extra == "all"
Requires-Dist: langchain-groq>=0.3.7; extra == "all"
Requires-Dist: groq>=0.31.0; extra == "all"
Dynamic: license-file
